pytest_aiohttp_mock/__init__.py
pytest_aiohttp_mock/_aiohttp_mock.py
pytest_aiohttp_mock/_options.py
pytest_aiohttp_mock/_pretty_print.py
pytest_aiohttp_mock/_request.py
pytest_aiohttp_mock/_request_matcher.py
pytest_aiohttp_mock/py.typed
pytest_aiohttp_mock-0.1.2.dist-info/METADATA
pytest_aiohttp_mock-0.1.2.dist-info/WHEEL
pytest_aiohttp_mock-0.1.2.dist-info/entry_points.txt
pytest_aiohttp_mock-0.1.2.dist-info/licenses/LICENSE
pytest_aiohttp_mock-0.1.2.dist-info/RECORD
