Metadata-Version: 2.4
Name: pytest-aiohttp-mock
Version: 0.1.2
Summary: Send responses to aiohttp.
Project-URL: Homepage, https://github.com/mvanderlee/pytest-aiohttp-mock
Author-email: Michiel Vanderlee <jmt.vanderlee@gmail.com>
License: MIT License
License-File: LICENSE
Keywords: aiohttp,mock,pytest,testing
Classifier: Development Status :: 3 - Alpha
Classifier: Framework :: Pytest
Classifier: Intended Audience :: Developers
Classifier: License :: OSI Approved :: MIT License
Classifier: Natural Language :: English
Classifier: Programming Language :: Python
Classifier: Programming Language :: Python :: 3
Classifier: Programming Language :: Python :: 3.10
Classifier: Programming Language :: Python :: 3.11
Classifier: Programming Language :: Python :: 3.12
Classifier: Programming Language :: Python :: 3.13
Classifier: Topic :: Internet :: WWW/HTTP
Classifier: Topic :: Software Development :: Build Tools
Classifier: Typing :: Typed
Requires-Python: >=3.10
Requires-Dist: aiohttp>=3.12.0
Requires-Dist: orjson>=3.10
Requires-Dist: pytest>=8
